Metadata-Version: 2.4
Name: tokenicer
Version: 0.0.5
Summary: A (nicer) tokenizer you want to use for model `inference` and `training`: with all known peventable `gotchas` normalized or auto-fixed.
Home-page: https://github.com/ModelCloud/Tokenicer
Author: ModelCloud
Author-email: qubitium@modelcloud.ai
Classifier: Programming Language :: Python :: 3
Classifier: License :: OSI Approved :: Apache Software License
Classifier: Operating System :: OS Independent
Requires-Python: >=3
License-File: LICENSE
Requires-Dist: transformers
Dynamic: author
Dynamic: author-email
Dynamic: classifier
Dynamic: description
Dynamic: description-content-type
Dynamic: home-page
Dynamic: license-file
Dynamic: requires-dist
Dynamic: requires-python
Dynamic: summary
